nixtlats/__init__.py
nixtlats/_modidx.py
nixtlats/client.py
nixtlats/date_features.py
nixtlats/nixtla_client.py
nixtlats/py.typed
nixtlats/utils.py
nixtlats/core/__init__.py
nixtlats/core/api_error.py
nixtlats/core/client_wrapper.py
nixtlats/core/datetime_utils.py
nixtlats/core/file.py
nixtlats/core/http_client.py
nixtlats/core/jsonable_encoder.py
nixtlats/core/pydantic_utilities.py
nixtlats/core/remove_none_from_dict.py
nixtlats/core/request_options.py
nixtlats/distributed/__init__.py
nixtlats/distributed/nixtla_client.py
nixtlats/errors/__init__.py
nixtlats/errors/unprocessable_entity_error.py
nixtlats/types/__init__.py
nixtlats/types/http_validation_error.py
nixtlats/types/model.py
nixtlats/types/multi_series_anomaly.py
nixtlats/types/multi_series_cross_validation.py
nixtlats/types/multi_series_cross_validation_fewshot_loss.py
nixtlats/types/multi_series_cross_validation_finetune_loss.py
nixtlats/types/multi_series_forecast.py
nixtlats/types/multi_series_forecast_fewshot_loss.py
nixtlats/types/multi_series_forecast_finetune_loss.py
nixtlats/types/multi_series_input.py
nixtlats/types/multi_series_insample_forecast.py
nixtlats/types/single_series_forecast.py
nixtlats/types/single_series_forecast_fewshot_loss.py
nixtlats/types/single_series_forecast_finetune_loss.py
nixtlats/types/single_series_insample_forecast.py
nixtlats/types/validation_error.py
nixtlats/types/validation_error_loc_item.py
nixtlats-0.5.2.dist-info/LICENSE
nixtlats-0.5.2.dist-info/METADATA
nixtlats-0.5.2.dist-info/WHEEL
nixtlats-0.5.2.dist-info/top_level.txt
nixtlats-0.5.2.dist-info/RECORD
