Metadata-Version: 2.1
Name: nixtlats
Version: 0.5.2
Summary: Python SDK for Nixtla API (TimeGPT)
Home-page: https://github.com/Nixtla/nixtla
Classifier: Programming Language :: Python :: 3
Classifier: License :: OSI Approved :: MIT License
Classifier: Operating System :: OS Independent
Requires-Python: >=3.8
License-File: LICENSE
Requires-Dist: httpx
Requires-Dist: pandas
Requires-Dist: pydantic
Requires-Dist: requests
Requires-Dist: tenacity
Requires-Dist: utilsforecast >=0.1.7
Provides-Extra: date_extras
Requires-Dist: holidays ; extra == 'date_extras'
Provides-Extra: dev
Requires-Dist: black ; extra == 'dev'
Requires-Dist: datasetsforecast ; extra == 'dev'
Requires-Dist: nbdev ; extra == 'dev'
Requires-Dist: plotly ; extra == 'dev'
Requires-Dist: pre-commit ; extra == 'dev'
Requires-Dist: python-dotenv ; extra == 'dev'
Requires-Dist: pyreadr ; extra == 'dev'
Requires-Dist: statsforecast ; extra == 'dev'
Requires-Dist: neuralforecast ; extra == 'dev'
Requires-Dist: hierarchicalforecast ; extra == 'dev'
Requires-Dist: jupyterlab ; extra == 'dev'
Requires-Dist: setuptools <70 ; extra == 'dev'
Requires-Dist: dask[dataframe] ; extra == 'dev'
Requires-Dist: fugue[ray] >=0.8.7 ; extra == 'dev'
Requires-Dist: pyspark ; extra == 'dev'
Requires-Dist: ray[serve-grpc] ; extra == 'dev'
Requires-Dist: utilsforecast[plotting] >=0.1.7 ; extra == 'dev'
Requires-Dist: holidays ; extra == 'dev'
Provides-Extra: distributed
Requires-Dist: dask[dataframe] ; extra == 'distributed'
Requires-Dist: fugue[ray] >=0.8.7 ; extra == 'distributed'
Requires-Dist: pyspark ; extra == 'distributed'
Requires-Dist: ray[serve-grpc] ; extra == 'distributed'
Provides-Extra: plotting
Requires-Dist: utilsforecast[plotting] >=0.1.7 ; extra == 'plotting'
